artissist_logger/__init__.py
artissist_logger/context.py
artissist_logger/emoji.py
artissist_logger/factory.py
artissist_logger/logger.py
artissist_logger/types.py
artissist_logger/adapters/__init__.py
artissist_logger/adapters/base.py
artissist_logger/adapters/console.py
artissist_logger/adapters/file.py
artissist_logger-0.1.2.dist-info/METADATA
artissist_logger-0.1.2.dist-info/WHEEL
artissist_logger-0.1.2.dist-info/entry_points.txt
artissist_logger-0.1.2.dist-info/top_level.txt
artissist_logger-0.1.2.dist-info/RECORD
