Metadata-Version: 2.4
Name: artissist-logger
Version: 0.1.2
Summary: Platform-agnostic logging client for Artissist
Home-page: https://github.com/artissist/logger
Author: Artissist
Author-email: dev@artissist.com
Project-URL: Bug Reports, https://github.com/artissist/logger/issues
Project-URL: Source, https://github.com/artissist/logger
Project-URL: Documentation, https://github.com/artissist/logger
Keywords: logging,observability,telemetry,platform,artissist
Classifier: Development Status :: 4 - Beta
Classifier: Intended Audience :: Developers
Classifier: Topic :: Software Development :: Libraries :: Python Modules
Classifier: Topic :: System :: Logging
Classifier: License :: OSI Approved :: MIT License
Classifier: Programming Language :: Python :: 3
Classifier: Programming Language :: Python :: 3.8
Classifier: Programming Language :: Python :: 3.9
Classifier: Programming Language :: Python :: 3.10
Classifier: Programming Language :: Python :: 3.11
Classifier: Programming Language :: Python :: 3.12
Requires-Python: >=3.8
Requires-Dist: typing_extensions>=4.0.0
Requires-Dist: dataclasses; python_version < "3.7"
Provides-Extra: dev
Requires-Dist: pytest>=7.0.0; extra == "dev"
Requires-Dist: pytest-cov>=4.0.0; extra == "dev"
Requires-Dist: pytest-asyncio>=0.21.0; extra == "dev"
Requires-Dist: black>=22.0.0; extra == "dev"
Requires-Dist: mypy>=1.0.0; extra == "dev"
Requires-Dist: flake8>=5.0.0; extra == "dev"
Requires-Dist: pylint>=2.15.0; extra == "dev"
Requires-Dist: types-aiofiles>=22.0.0; extra == "dev"
Requires-Dist: aiofiles>=22.0.0; extra == "dev"
Provides-Extra: file
Requires-Dist: aiofiles>=22.0.0; extra == "file"
Provides-Extra: cloud
Requires-Dist: boto3>=1.26.0; extra == "cloud"
Requires-Dist: azure-monitor-opentelemetry-exporter>=1.0.0b17; extra == "cloud"
Requires-Dist: google-cloud-logging>=3.4.0; extra == "cloud"
Dynamic: author
Dynamic: author-email
Dynamic: classifier
Dynamic: description
Dynamic: description-content-type
Dynamic: home-page
Dynamic: keywords
Dynamic: project-url
Dynamic: provides-extra
Dynamic: requires-dist
Dynamic: requires-python
Dynamic: summary
